HISTORY.rst
LICENSE
MANIFEST.in
README.md
requirements.txt
setup.py
contexture/__init__.py
contexture/config.conf
contexture/context.py
contexture/monitor.py
contexture/settings.py
contexture.egg-info/PKG-INFO
contexture.egg-info/SOURCES.txt
contexture.egg-info/dependency_links.txt
contexture.egg-info/entry_points.txt
contexture.egg-info/requires.txt
contexture.egg-info/top_level.txt
contexture/analytics/__init__.py
contexture/analytics/errorcount.py
contexture/analytics/es.py
contexture/backend/__init__.py
contexture/backend/amqp.py
contexture/backend/amqp_puka.py
contexture/utils/__init__.py
contexture/utils/db.py
test/__init__.py
test/test_amqp.py
test/test_context.py
test/test_utils.py