Metadata-Version: 1.0
Name: contexture
Version: 1.2
Summary: Magic Automatic Logging Context
Home-page: https://github.com/unthingable/contexture
Author: Alex Kouznetsov
Author-email: alex@eat-up.org
License: Apache 2
Platform: UNKNOWN
